Metadata-Version: 1.1
Name: ECLAIR
Version: 1.11
Summary: Robust inference of cell lineages from gene expression data via consensus clustering and the aggregation of ensembles of minimum spanning trees.
Home-page: https://github.com/GGiecold/ECLAIR
Author: Gregory Giecold
Author-email: ggiecold@jimmy.harvard.edu
License: MIT License
Download-URL: https://github.com/GGiecold/ECLAIR
Keywords: aggregation bio-informatics clustering computational-biology consensus consensus-clustering cytometry data-mining ensemble ensemble-clustering gene gene-expression graph graph-matching machine-learning matching pattern-recognition qPCR tree tree-matching unsupervised-learning
Platform: Any
Classifier: Development Status :: 4 - Beta
Classifier: Environment :: Console
Classifier: Intended Audience :: End Users/Desktop
Classifier: Intended Audience :: Developers
Classifier: Intended Audience :: Science/Research
Classifier: License :: OSI Approved :: MIT License
Classifier: Natural Language :: English
Classifier: Operating System :: MacOS :: MacOS X
Classifier: Operating System :: POSIX
Classifier: Programming Language :: Python :: 2.7
Classifier: Topic :: Scientific/Engineering
Classifier: Topic :: Scientific/Engineering :: Bio-Informatics
Classifier: Topic :: Scientific/Engineering :: Visualization
Classifier: Topic :: Scientific/Engineering :: Mathematics
